lottie_specs/__init__.py
lottie_specs/codegen.py
lottie_specs/resources.py
lottie_specs/schema.py
lottie_specs/type_info.py
lottie_specs/code_processing/loader.py
lottie_specs/code_processing/pseudocode.py
lottie_specs/data/lottie.schema.json
lottie_specs/markdown/latex_markdown.py
lottie_specs/markdown/lottie_markdown.py
lottie_specs/markdown/toc_deflist.py
lottie_specs-0.5.1.data/scripts/enumerate-props.py
lottie_specs-0.5.1.data/scripts/render_shape.py
lottie_specs-0.5.1.data/scripts/schema-merge.py
lottie_specs-0.5.1.data/scripts/schema-validate.py
lottie_specs-0.5.1.dist-info/licenses/COPYING
lottie_specs-0.5.1.dist-info/METADATA
lottie_specs-0.5.1.dist-info/WHEEL
lottie_specs-0.5.1.dist-info/top_level.txt
lottie_specs-0.5.1.dist-info/RECORD
