Metadata-Version: 2.4
Name: lottie_specs
Version: 0.5.1
Summary: Tools to load the Lottie standard specs
Home-page: https://github.com/lottie/lottie-specs-python
Author: Lottie Animation Community
Project-URL: Bug Reports, https://github.com/lottie/lottie-specs-python/issues
Project-URL: Source, https://github.com/lottie/lottie-specs-python
Requires-Python: >=3.10, <4
License-File: COPYING
Provides-Extra: docs
Requires-Dist: lxml==5.4.0; extra == "docs"
Requires-Dist: html5lib==1.1; extra == "docs"
Requires-Dist: source_translator==1.0.1; extra == "docs"
Requires-Dist: graphviz==0.20.1; extra == "docs"
Requires-Dist: mkdocs==1.6.1; extra == "docs"
Requires-Dist: latex2mathml==3.77.0; extra == "docs"
Provides-Extra: render
Requires-Dist: lottie==0.7.2; extra == "render"
Requires-Dist: source_translator==1.1.0; extra == "render"
Dynamic: author
Dynamic: description
Dynamic: description-content-type
Dynamic: home-page
Dynamic: license-file
Dynamic: project-url
Dynamic: provides-extra
Dynamic: requires-python
Dynamic: summary
